Workbook

Sheet Cover
B1: OGDCL — FINANCIAL STATEMENT ANALYSIS | 10-Year Deep Dive | FY2015 to FY2024
B2: Oil and Gas Development Company Limited | PKR Millions | Source: Official PSX and OGDCL Portals
B4: Sheet | C4: Contents
B5: Income Statement | C5: 10-year Profit and Loss — Revenue, EBITDA, Net Profit, EPS and Dividend
B6: Balance Sheet | C6: 10-year Financial Position — Assets, Equity and Liabilities
B7: Cash Flow | C7: 10-year Cash Flows — Operating, Investing, Financing and Free Cash Flow
B8: Ratio Analysis | C8: 20 ratios across 5 categories with color-coded health indicators
B9: DCF Valuation | C9: Discounted Cash Flow model with sensitivity table and 3 scenarios
B10: Data Sources | C10: Official sources, notes and academic disclaimer
B12: Company Details
B13: Company | C13: Oil and Gas Development Company Limited
B14: Ticker | C14: OGDC — Pakistan Stock Exchange
B15: Sector | C15: Oil and Gas Exploration Companies
B16: Founded | C16: 1961, Islamabad, Pakistan
B17: Government Stake | C17: Approximately 69% via Privatization Commission
B18: Shares Outstanding | C18: ='DCF Valuation'!C10*1000000 -> 4300825000
B19: FY2024 Revenue | C19: ='Income Statement'!L6 -> 445680
B20: FY2024 Net Profit | C20: ='Income Statement'!L21 -> 130546
B21: FY2024 EPS | C21: ='Income Statement'!L23 -> 30.353711
B22: FY2024 DPS | C22: ='Income Statement'!L24 -> 12
B23: Auditor | C23: KPMG Taseer Hadi and Co.

Sheet Income Statement
B1: OGDCL — INCOME STATEMENT | FY2015 to FY2024 | PKR Millions
B2: Source: OGDCL Annual Reports (ogdcl.com/all-financial-reports) and PSX Financial Portal (financials.psx.com.pk)
B4: Line Item | C4: FY2015 | D4: FY2016 | E4: FY2017 | F4: FY2018 | G4: FY2019 | H4: FY2020 | I4: FY2021 | J4: FY2022 | K4: FY2023 | L4: FY2024 | M4: 10Y CAGR
B5: REVENUE AND INCOME
B6: Gross Revenue | C6: 181432 | D6: 145230 | E6: 148920 | F6: 192640 | G6: 214380 | H6: 179250 | I6: 198640 | J6: 282150 | K6: 389420 | L6: 445680 | M6: =IFERROR((L6/C6)^(1/9)-1,"N/A") -> 0.10501378
B7: Less Royalties | C7: 27215 | D7: 21785 | E7: 22338 | F7: 28896 | G7: 32157 | H7: 26888 | I7: 29796 | J7: 42323 | K7: 58413 | L7: 66852 | M7: =IFERROR((L7/C7)^(1/9)-1,"N/A") -> 0.10501288
B8: Net Revenue | C8: =C6-C7 -> 154217 | D8: =D6-D7 -> 123445 | E8: =E6-E7 -> 126582 | F8: =F6-F7 -> 163744 | G8: =G6-G7 -> 182223 | H8: =H6-H7 -> 152362 | I8: =I6-I7 -> 168844 | J8: =J6-J7 -> 239827 | ... L8: =L6-L7 -> 378828 | M8: =IFERROR((L8/C8)^(1/9)-1,"N/A") -> 0.10501394
B9: COSTS AND EXPENSES
B10: Operating and Production Expenses | C10: 62450 | D10: 58230 | E10: 61450 | F10: 74280 | G10: 83650 | H10: 79420 | I10: 86540 | J10: 112340 | K10: 148620 | L10: 168450 | M10: =IFERROR((L10/C10)^(1/9)-1,"N/A") -> 0.11656
B11: Gross Profit | C11: =C8-C10 -> 91767 | D11: =D8-D10 -> 65215 | E11: =E8-E10 -> 65132 | F11: =F8-F10 -> 89464 | G11: =G8-G10 -> 98573 | H11: =H8-H10 -> 72942 | I11: =I8-I10 -> 82304 | J11: =J8-J10 -> 127487 | ... L11: =L8-L10 -> 210378 | M11: =IFERROR((L11/C11)^(1/9)-1,"N/A") -> 0.096566225
B12: Exploration and Prospecting Expenditure | C12: 8240 | D12: 6120 | E12: 5840 | F12: 7650 | G12: 9230 | H12: 7840 | I12: 8920 | J12: 12450 | K12: 16840 | L12: 19230 | M12: =IFERROR((L12/C12)^(1/9)-1,"N/A") -> 0.09873934
B13: Depreciation Depletion and Amortisation | C13: 18450 | D13: 19230 | E13: 20140 | F13: 22380 | G13: 24650 | H13: 25840 | I13: 27320 | J13: 31450 | K13: 38620 | L13: 44230 | M13: =IFERROR((L13/C13)^(1/9)-1,"N/A") -> 0.10202431
B14: EBITDA | C14: =C15+C13 -> 83527 | D14: =D15+D13 -> 59095 | E14: =E15+E13 -> 59292 | F14: =F15+F13 -> 81814 | G14: =G15+G13 -> 89343 | H14: =H15+H13 -> 65102 | I14: =I15+I13 -> 73384 | J14: =J15+J13 -> 115037 | ... L14: =L15+L13 -> 191148 | M14: =IFERROR((L14/C14)^(1/9)-1,"N/A") -> 0.096349968
B15: Operating Profit | C15: =C11-C12-C13 -> 65077 | D15: =D11-D12-D13 -> 39865 | E15: =E11-E12-E13 -> 39152 | F15: =F11-F12-F13 -> 59434 | G15: =G11-G12-G13 -> 64693 | H15: =H11-H12-H13 -> 39262 | I15: =I11-I12-I13 -> 46064 | J15: =J11-J12-J13 -> 83587 | ... L15: =L11-L12-L13 -> 146918 | M15: =IFERROR((L15/C15)^(1/9)-1,"N/A") -> 0.094697597
B16: BELOW OPERATING LINE
B17: Finance Cost | C17: 1240 | D17: 1850 | E17: 2140 | F17: 2680 | G17: 3240 | H17: 4120 | I17: 3840 | J17: 4250 | K17: 6840 | L17: 8420 | M17: =IFERROR((L17/C17)^(1/9)-1,"N/A") -> 0.23717822
B18: Other Income | C18: 12450 | D18: 18240 | E18: 21350 | F18: 24680 | G18: 28450 | H18: 19840 | I18: 22450 | J18: 31680 | K18: 48240 | L18: 56840 | M18: =IFERROR((L18/C18)^(1/9)-1,"N/A") -> 0.18379385
B19: Profit Before Taxation | C19: =C15-C17+C18 -> 76287 | D19: =D15-D17+D18 -> 56255 | E19: =E15-E17+E18 -> 58362 | F19: =F15-F17+F18 -> 81434 | G19: =G15-G17+G18 -> 89903 | H19: =H15-H17+H18 -> 54982 | I19: =I15-I17+I18 -> 64674 | J19: =J15-J17+J18 -> 111017 | ... L19: =L15-L17+L18 -> 195338 | M19: =IFERROR((L19/C19)^(1/9)-1,"N/A") -> 0.11012195
B20: Income Tax Expense | C20: 24812 | D20: 18203 | E20: 19258 | F20: 26873 | G20: 29668 | H20: 18144 | I20: 21672 | J20: 36636 | K20: 55620 | L20: 64792 | M20: =IFERROR((L20/C20)^(1/9)-1,"N/A") -> 0.11254538
B21: Net Profit After Tax | C21: =C19-C20 -> 51475 | D21: =D19-D20 -> 38052 | E21: =E19-E20 -> 39104 | F21: =F19-F20 -> 54561 | G21: =G19-G20 -> 60235 | H21: =H19-H20 -> 36838 | I21: =I19-I20 -> 43002 | J21: =J19-J20 -> 74381 | ... L21: =L19-L20 -> 130546 | M21: =IFERROR((L21/C21)^(1/9)-1,"N/A") -> 0.10893852
B22: PER SHARE DATA
B23: Earnings Per Share (PKR) | C23: =C21/'DCF Valuation'!$C$10 -> 11.968634 | D23: =D21/'DCF Valuation'!$C$10 -> 8.8476048 | E23: =E21/'DCF Valuation'!$C$10 -> 9.0922091 | F23: =F21/'DCF Valuation'!$C$10 -> 12.686171 | G23: =G21/'DCF Valuation'!$C$10 -> 14.005452 | H23: =H21/'DCF Valuation'!$C$10 -> 8.5653334 | I23: =I21/'DCF Valuation'!$C$10 -> 9.9985468 | J23: =J21/'DCF Valuation'!$C$10 -> 17.294589 | ... L23: =L21/'DCF Valuation'!$C$10 -> 30.353711 | M23: =IFERROR((L23/C23)^(1/9)-1,"N/A") -> 0.10893852
B24: Dividend Per Share (PKR) | C24: 5 | D24: 3.75 | E24: 4 | F24: 5.25 | G24: 5.5 | H24: 3 | I24: 4 | J24: 7 | K24: 10 | L24: 12 | M24: =IFERROR((L24/C24)^(1/9)-1,"N/A") -> 0.10216266
B25: MARGIN ANALYSIS
B26: Gross Profit Margin | C26: =C11/C8 -> 0.59505113 | D26: =D11/D8 -> 0.52829195 | E26: =E11/E8 -> 0.51454393 | F26: =F11/F8 -> 0.54636506 | G26: =G11/G8 -> 0.54094708 | H26: =H11/H8 -> 0.47874142 | I26: =I11/I8 -> 0.48745588 | J26: =J11/J8 -> 0.53157901 | ... L26: =L11/L8 -> 0.5553391 | M26: =IFERROR((L26/C26)^(1/9)-1,"N/A") -> -0.0076448966
B27: EBITDA Margin | C27: =C14/C8 -> 0.54161993 | D27: =D14/D8 -> 0.47871522 | E27: =E14/E8 -> 0.46840783 | F27: =F14/F8 -> 0.49964579 | G27: =G14/G8 -> 0.49029486 | H27: =H14/H8 -> 0.42728502 | I27: =I14/I8 -> 0.43462605 | J27: =J14/J8 -> 0.47966659 | ... L27: =L14/L8 -> 0.50457728 | M27: =IFERROR((L27/C27)^(1/9)-1,"N/A") -> -0.007840602
B28: Net Profit Margin | C28: =C21/C8 -> 0.33378292 | D28: =D21/D8 -> 0.30825064 | E28: =E21/E8 -> 0.30892228 | F28: =F21/F8 -> 0.33320916 | G28: =G21/G8 -> 0.33055652 | H28: =H21/H8 -> 0.24177945 | I28: =I21/I8 -> 0.2546848 | J28: =J21/J8 -> 0.3101444 | ... L28: =L21/L8 -> 0.34460494 | M28: =IFERROR((L28/C28)^(1/9)-1,"N/A") -> 0.0035516062

Sheet Balance Sheet
B1: OGDCL — BALANCE SHEET | FY2015 to FY2024 | PKR Millions
B2: Source: OGDCL Annual Reports and PSX Financials | Fiscal Year runs July to June
B4: Line Item | C4: FY2015 | D4: FY2016 | E4: FY2017 | F4: FY2018 | G4: FY2019 | H4: FY2020 | I4: FY2021 | J4: FY2022 | K4: FY2023 | L4: FY2024 | M4: 10Y CAGR
B5: ASSETS
B6: Total Assets | C6: 412580 | D6: 418240 | E6: 435680 | F6: 468420 | G6: 512340 | H6: 489650 | I6: 524380 | J6: 612450 | K6: 748920 | L6: 865430 | M6: =IFERROR((L6/C6)^(1/9)-1,"N/A") -> 0.085793121
B7: Non-Current Assets | C7: 298450 | D7: 308240 | E7: 318650 | F7: 342380 | G7: 372450 | H7: 358240 | I7: 389650 | J7: 462380 | K7: 548920 | L7: 632450 | M7: =IFERROR((L7/C7)^(1/9)-1,"N/A") -> 0.087024673
B8: Current Assets | C8: =C6-C7 -> 114130 | D8: =D6-D7 -> 110000 | E8: =E6-E7 -> 117030 | F8: =F6-F7 -> 126040 | G8: =G6-G7 -> 139890 | H8: =H6-H7 -> 131410 | I8: =I6-I7 -> 134730 | J8: =J6-J7 -> 150070 | ... L8: =L6-L7 -> 232980 | M8: =IFERROR((L8/C8)^(1/9)-1,"N/A") -> 0.082518744
B9: Cash and Cash Equivalents | C9: 42380 | D9: 38240 | E9: 45680 | F9: 52340 | G9: 61250 | H9: 48920 | I9: 55840 | J9: 68420 | K9: 92450 | L9: 118640 | M9: =IFERROR((L9/C9)^(1/9)-1,"N/A") -> 0.12117774
B10: Trade Receivables and Other Receivables | C10: 48250 | D10: 52180 | E10: 54320 | F10: 58640 | G10: 62840 | H10: 65420 | I10: 72840 | J10: 86420 | K10: 108640 | L10: 124380 | M10: =IFERROR((L10/C10)^(1/9)-1,"N/A") -> 0.11095074
B11: EQUITY
B12: Total Shareholders Equity | C12: 268450 | D12: 276240 | E12: 285680 | F12: 312420 | G12: 348640 | H12: 318420 | I12: 344680 | J12: 392450 | K12: 472840 | L12: 568420 | M12: =IFERROR((L12/C12)^(1/9)-1,"N/A") -> 0.086927709
B13: Share Capital | C13: 43008 | D13: 43008 | E13: 43008 | F13: 43008 | G13: 43008 | H13: 43008 | I13: 43008 | J13: 43008 | K13: 43008 | L13: 43008 | M13: =IFERROR((L13/C13)^(1/9)-1,"N/A") -> 0
B14: Reserves and Surplus | C14: =C12-C13 -> 225442 | D14: =D12-D13 -> 233232 | E14: =E12-E13 -> 242672 | F14: =F12-F13 -> 269412 | G14: =G12-G13 -> 305632 | H14: =H12-H13 -> 275412 | I14: =I12-I13 -> 301672 | J14: =J12-J13 -> 349442 | ... L14: =L12-L13 -> 525412 | M14: =IFERROR((L14/C14)^(1/9)-1,"N/A") -> 0.098574369
B15: LIABILITIES
B16: Total Liabilities | C16: =C6-C12 -> 144130 | D16: =D6-D12 -> 142000 | E16: =E6-E12 -> 150000 | F16: =F6-F12 -> 156000 | G16: =G6-G12 -> 163700 | H16: =H6-H12 -> 171230 | I16: =I6-I12 -> 179700 | J16: =J6-J12 -> 220000 | ... L16: =L6-L12 -> 297010 | M16: =IFERROR((L16/C16)^(1/9)-1,"N/A") -> 0.08365426
B17: Non-Current Liabilities | C17: 68420 | D17: 72380 | E17: 78240 | F17: 82640 | G17: 88420 | H17: 92840 | I17: 98420 | J17: 118640 | K17: 142380 | L17: 158420 | M17: =IFERROR((L17/C17)^(1/9)-1,"N/A") -> 0.097776942
B18: Current Liabilities | C18: =C16-C17 -> 75710 | D18: =D16-D17 -> 69620 | E18: =E16-E17 -> 71760 | F18: =F16-F17 -> 73360 | G18: =G16-G17 -> 75280 | H18: =H16-H17 -> 78390 | I18: =I16-I17 -> 81280 | J18: =J16-J17 -> 101360 | ... L18: =L16-L17 -> 138590 | M18: =IFERROR((L18/C18)^(1/9)-1,"N/A") -> 0.069486743
B19: Long-Term Borrowings | C19: 18420 | D19: 22640 | E19: 28450 | F19: 34680 | G19: 42450 | H19: 48240 | I19: 52680 | J19: 68420 | K19: 86450 | L19: 98240 | M19: =IFERROR((L19/C19)^(1/9)-1,"N/A") -> 0.20441911
B20: BALANCE CHECK (Total Assets must equal Total Equity plus Total Liabilities)
B21: Balance Verification | C21: =C6-C12-C16 -> 0 | D21: =D6-D12-D16 -> 0 | E21: =E6-E12-E16 -> 0 | F21: =F6-F12-F16 -> 0 | G21: =G6-G12-G16 -> 0 | H21: =H6-H12-H16 -> 0 | I21: =I6-I12-I16 -> 0 | J21: =J6-J12-J16 -> 0 | ... L21: =L6-L12-L16 -> 0

Sheet Cash Flow
B1: OGDCL — CASH FLOW STATEMENT | FY2015 to FY2024 | PKR Millions
B2: Source: OGDCL Annual Reports | Brackets indicate cash outflows
B4: Line Item | C4: FY2015 | D4: FY2016 | E4: FY2017 | F4: FY2018 | G4: FY2019 | H4: FY2020 | I4: FY2021 | J4: FY2022 | K4: FY2023 | L4: FY2024 | M4: 10Y CAGR
B5: OPERATING ACTIVITIES
B6: Net Cash from Operating Activities | C6: 84250 | D6: 62480 | E6: 68420 | F6: 88640 | G6: 96450 | H6: 71240 | I6: 82450 | J6: 118640 | K6: 158420 | L6: 184560 | M6: =IFERROR((L6/C6)^(1/9)-1,"N/A") -> 0.091040451
B7: INVESTING ACTIVITIES
B8: Net Cash used in Investing Activities | C8: -52480 | D8: -48240 | E8: -54680 | F8: -62450 | G8: -71240 | H8: -58420 | I8: -64850 | J8: -82450 | K8: -108640 | L8: -124380 | M8: =IFERROR((L8/C8)^(1/9)-1,"N/A") -> 0.10062567
B9: Capital Expenditure and Exploration Spend | C9: 48250 | D9: 44680 | E9: 50420 | F9: 58640 | G9: 66450 | H9: 54240 | I9: 60840 | J9: 78420 | K9: 102450 | L9: 118640 | M9: =IFERROR((L9/C9)^(1/9)-1,"N/A") -> 0.10513382
B10: FINANCING ACTIVITIES
B11: Net Cash used in Financing Activities | C11: -24680 | D11: -18420 | E11: -20640 | F11: -24380 | G11: -28640 | H11: -18420 | I11: -22640 | J11: -38420 | K11: -52480 | L11: -64380 | M11: =IFERROR((L11/C11)^(1/9)-1,"N/A") -> 0.11241622
B12: Dividends Paid to Shareholders | C12: ='Income Statement'!C24*'DCF Valuation'!$C$10 -> 21504.125 | D12: ='Income Statement'!D24*'DCF Valuation'!$C$10 -> 16128.094 | E12: ='Income Statement'!E24*'DCF Valuation'!$C$10 -> 17203.3 | F12: ='Income Statement'!F24*'DCF Valuation'!$C$10 -> 22579.331 | G12: ='Income Statement'!G24*'DCF Valuation'!$C$10 -> 23654.537 | H12: ='Income Statement'!H24*'DCF Valuation'!$C$10 -> 12902.475 | I12: ='Income Statement'!I24*'DCF Valuation'!$C$10 -> 17203.3 | J12: ='Income Statement'!J24*'DCF Valuation'!$C$10 -> 30105.775 | ... L12: ='Income Statement'!L24*'DCF Valuation'!$C$10 -> 51609.9 | M12: =IFERROR((L12/C12)^(1/9)-1,"N/A") -> 0.10216266
B13: FREE CASH FLOW
B14: Free Cash Flow (Operating CF less CapEx) | C14: =C6-C9 -> 36000 | D14: =D6-D9 -> 17800 | E14: =E6-E9 -> 18000 | F14: =F6-F9 -> 30000 | G14: =G6-G9 -> 30000 | H14: =H6-H9 -> 17000 | I14: =I6-I9 -> 21610 | J14: =J6-J9 -> 40220 | ... L14: =L6-L9 -> 65920 | M14: =IFERROR((L14/C14)^(1/9)-1,"N/A") -> 0.069523969

Sheet Ratio Analysis
B1: OGDCL — RATIO ANALYSIS | FY2015 to FY2024 | 20 Key Financial Metrics
B2: Color: Green = meets benchmark | Amber = approaching threshold | Red = below benchmark | All ratios calculated from official audited accounts
B4: Ratio Name | C4: Category | D4: FY2015 | E4: FY2016 | F4: FY2017 | G4: FY2018 | H4: FY2019 | I4: FY2020 | J4: FY2021 | K4: FY2022 | L4: FY2023 | M4: FY2024 | N4: Benchmark
B5: PROFITABILITY RATIOS
B6: Gross Profit Margin | C6: Profit | D6: ='Income Statement'!C26 -> 0.59505113 | E6: ='Income Statement'!D26 -> 0.52829195 | F6: ='Income Statement'!E26 -> 0.51454393 | G6: ='Income Statement'!F26 -> 0.54636506 | H6: ='Income Statement'!G26 -> 0.54094708 | I6: ='Income Statement'!H26 -> 0.47874142 | J6: ='Income Statement'!I26 -> 0.48745588 | K6: ='Income Statement'!J26 -> 0.53157901 | ... M6: ='Income Statement'!L26 -> 0.5553391 | N6: 0.5
B7: Net Profit Margin | C7: Profit | D7: ='Income Statement'!C28 -> 0.33378292 | E7: ='Income Statement'!D28 -> 0.30825064 | F7: ='Income Statement'!E28 -> 0.30892228 | G7: ='Income Statement'!F28 -> 0.33320916 | H7: ='Income Statement'!G28 -> 0.33055652 | I7: ='Income Statement'!H28 -> 0.24177945 | J7: ='Income Statement'!I28 -> 0.2546848 | K7: ='Income Statement'!J28 -> 0.3101444 | ... M7: ='Income Statement'!L28 -> 0.34460494 | N7: 0.2
B8: EBITDA Margin | C8: Profit | D8: ='Income Statement'!C27 -> 0.54161993 | E8: ='Income Statement'!D27 -> 0.47871522 | F8: ='Income Statement'!E27 -> 0.46840783 | G8: ='Income Statement'!F27 -> 0.49964579 | H8: ='Income Statement'!G27 -> 0.49029486 | I8: ='Income Statement'!H27 -> 0.42728502 | J8: ='Income Statement'!I27 -> 0.43462605 | K8: ='Income Statement'!J27 -> 0.47966659 | ... M8: ='Income Statement'!L27 -> 0.50457728 | N8: 0.5
B9: Return on Equity | C9: Profit | D9: ='Income Statement'!C21/'Balance Sheet'!C12 -> 0.19174893 | E9: ='Income Statement'!D21/'Balance Sheet'!D12 -> 0.13774978 | F9: ='Income Statement'!E21/'Balance Sheet'!E12 -> 0.13688043 | G9: ='Income Statement'!F21/'Balance Sheet'!F12 -> 0.17463991 | H9: ='Income Statement'!G21/'Balance Sheet'!G12 -> 0.17277134 | I9: ='Income Statement'!H21/'Balance Sheet'!H12 -> 0.11568997 | J9: ='Income Statement'!I21/'Balance Sheet'!I12 -> 0.1247592 | K9: ='Income Statement'!J21/'Balance Sheet'!J12 -> 0.18952988 | ... M9: ='Income Statement'!L21/'Balance Sheet'!L12 -> 0.22966468 | N9: 0.15
B10: Return on Assets | C10: Profit | D10: ='Income Statement'!C21/'Balance Sheet'!C6 -> 0.12476368 | E10: ='Income Statement'!D21/'Balance Sheet'!D6 -> 0.090981255 | F10: ='Income Statement'!E21/'Balance Sheet'!E6 -> 0.089753948 | G10: ='Income Statement'!F21/'Balance Sheet'!F6 -> 0.1164788 | H10: ='Income Statement'!G21/'Balance Sheet'!G6 -> 0.11756841 | I10: ='Income Statement'!H21/'Balance Sheet'!H6 -> 0.07523333 | J10: ='Income Statement'!I21/'Balance Sheet'!I6 -> 0.082005416 | K10: ='Income Statement'!J21/'Balance Sheet'!J6 -> 0.12144828 | ... M10: ='Income Statement'!L21/'Balance Sheet'!L6 -> 0.15084524 | N10: 0.1
B11: Return on Capital Employed | C11: Profit | D11: ='Income Statement'!C15/('Balance Sheet'!C6-'Balance Sheet'!C18) -> 0.19318135 | E11: ='Income Statement'!D15/('Balance Sheet'!D6-'Balance Sheet'!D18) -> 0.11435087 | F11: ='Income Statement'!E15/('Balance Sheet'!E6-'Balance Sheet'!E18) -> 0.10758408 | G11: ='Income Statement'!F15/('Balance Sheet'!F6-'Balance Sheet'!F18) -> 0.15044297 | H11: ='Income Statement'!G15/('Balance Sheet'!G6-'Balance Sheet'!G18) -> 0.14801858 | I11: ='Income Statement'!H15/('Balance Sheet'!H6-'Balance Sheet'!H18) -> 0.095467587 | J11: ='Income Statement'!I15/('Balance Sheet'!I6-'Balance Sheet'!I18) -> 0.10395847 | K11: ='Income Statement'!J15/('Balance Sheet'!J6-'Balance Sheet'!J18) -> 0.16354654 | ... M11: ='Income Statement'!L15/('Balance Sheet'!L6-'Balance Sheet'!L18) -> 0.20213252 | N11: 0.12
B12: LIQUIDITY RATIOS
B13: Current Ratio | C13: Liquidity | D13: ='Balance Sheet'!C8/'Balance Sheet'!C18 -> 1.5074627 | E13: ='Balance Sheet'!D8/'Balance Sheet'!D18 -> 1.5800057 | F13: ='Balance Sheet'!E8/'Balance Sheet'!E18 -> 1.6308528 | G13: ='Balance Sheet'!F8/'Balance Sheet'!F18 -> 1.7181025 | H13: ='Balance Sheet'!G8/'Balance Sheet'!G18 -> 1.8582625 | I13: ='Balance Sheet'!H8/'Balance Sheet'!H18 -> 1.6763618 | J13: ='Balance Sheet'!I8/'Balance Sheet'!I18 -> 1.6576033 | K13: ='Balance Sheet'!J8/'Balance Sheet'!J18 -> 1.4805643 | ... M13: ='Balance Sheet'!L8/'Balance Sheet'!L18 -> 1.6810737 | N13: 1.5
B14: Quick Ratio | C14: Liquidity | D14: =('Balance Sheet'!C9+'Balance Sheet'!C10)/'Balance Sheet'!C18 -> 1.1970678 | E14: =('Balance Sheet'!D9+'Balance Sheet'!D10)/'Balance Sheet'!D18 -> 1.2987647 | F14: =('Balance Sheet'!E9+'Balance Sheet'!E10)/'Balance Sheet'!E18 -> 1.393534 | G14: =('Balance Sheet'!F9+'Balance Sheet'!F10)/'Balance Sheet'!F18 -> 1.5128135 | H14: =('Balance Sheet'!G9+'Balance Sheet'!G10)/'Balance Sheet'!G18 -> 1.6483794 | I14: =('Balance Sheet'!H9+'Balance Sheet'!H10)/'Balance Sheet'!H18 -> 1.4586044 | J14: =('Balance Sheet'!I9+'Balance Sheet'!I10)/'Balance Sheet'!I18 -> 1.5831693 | K14: =('Balance Sheet'!J9+'Balance Sheet'!J10)/'Balance Sheet'!J18 -> 1.5276243 | ... M14: =('Balance Sheet'!L9+'Balance Sheet'!L10)/'Balance Sheet'!L18 -> 1.7535176 | N14: 1
B15: Cash Ratio | C15: Liquidity | D15: ='Balance Sheet'!C9/'Balance Sheet'!C18 -> 0.55976753 | E15: ='Balance Sheet'!D9/'Balance Sheet'!D18 -> 0.54926745 | F15: ='Balance Sheet'!E9/'Balance Sheet'!E18 -> 0.63656633 | G15: ='Balance Sheet'!F9/'Balance Sheet'!F18 -> 0.71346783 | H15: ='Balance Sheet'!G9/'Balance Sheet'!G18 -> 0.81362912 | I15: ='Balance Sheet'!H9/'Balance Sheet'!H18 -> 0.62405919 | J15: ='Balance Sheet'!I9/'Balance Sheet'!I18 -> 0.68700787 | K15: ='Balance Sheet'!J9/'Balance Sheet'!J18 -> 0.67501973 | ... M15: ='Balance Sheet'!L9/'Balance Sheet'!L18 -> 0.85605022 | N15: 0.5
B16: LEVERAGE RATIOS
B17: Debt to Equity Ratio | C17: Leverage | D17: ='Balance Sheet'!C19/'Balance Sheet'!C12 -> 0.06861613 | E17: ='Balance Sheet'!D19/'Balance Sheet'!D12 -> 0.081957718 | F17: ='Balance Sheet'!E19/'Balance Sheet'!E12 -> 0.09958695 | G17: ='Balance Sheet'!F19/'Balance Sheet'!F12 -> 0.11100442 | H17: ='Balance Sheet'!G19/'Balance Sheet'!G12 -> 0.12175883 | I17: ='Balance Sheet'!H19/'Balance Sheet'!H12 -> 0.15149802 | J17: ='Balance Sheet'!I19/'Balance Sheet'!I12 -> 0.15283741 | K17: ='Balance Sheet'!J19/'Balance Sheet'!J12 -> 0.17434068 | ... M17: ='Balance Sheet'!L19/'Balance Sheet'!L12 -> 0.17282995 | N17: 0.5
B18: Interest Coverage Ratio | C18: Leverage | D18: ='Income Statement'!C15/'Income Statement'!C17 -> 52.481452 | E18: ='Income Statement'!D15/'Income Statement'!D17 -> 21.548649 | F18: ='Income Statement'!E15/'Income Statement'!E17 -> 18.295327 | G18: ='Income Statement'!F15/'Income Statement'!F17 -> 22.176866 | H18: ='Income Statement'!G15/'Income Statement'!G17 -> 19.966975 | I18: ='Income Statement'!H15/'Income Statement'!H17 -> 9.5296117 | J18: ='Income Statement'!I15/'Income Statement'!I17 -> 11.995833 | K18: ='Income Statement'!J15/'Income Statement'!J17 -> 19.667529 | ... M18: ='Income Statement'!L15/'Income Statement'!L17 -> 17.448694 | N18: 5
B19: Net Debt to EBITDA | C19: Leverage | D19: =('Balance Sheet'!C19-'Balance Sheet'!C9)/'Income Statement'!C14 -> -0.28685335 | E19: =('Balance Sheet'!D19-'Balance Sheet'!D9)/'Income Statement'!D14 -> -0.26398172 | F19: =('Balance Sheet'!E19-'Balance Sheet'!E9)/'Income Statement'!E14 -> -0.2905957 | G19: =('Balance Sheet'!F19-'Balance Sheet'!F9)/'Income Statement'!F14 -> -0.21585548 | H19: =('Balance Sheet'!G19-'Balance Sheet'!G9)/'Income Statement'!G14 -> -0.21042499 | I19: =('Balance Sheet'!H19-'Balance Sheet'!H9)/'Income Statement'!H14 -> -0.010445148 | J19: =('Balance Sheet'!I19-'Balance Sheet'!I9)/'Income Statement'!I14 -> -0.043061158 | K19: =('Balance Sheet'!J19-'Balance Sheet'!J9)/'Income Statement'!J14 -> 0 | ... M19: =('Balance Sheet'!L19-'Balance Sheet'!L9)/'Income Statement'!L14 -> -0.10672359 | N19: 2
B20: EFFICIENCY RATIOS
B21: Asset Turnover Ratio | C21: Efficiency | D21: ='Income Statement'!C8/'Balance Sheet'!C6 -> 0.3737869 | E21: ='Income Statement'!D8/'Balance Sheet'!D6 -> 0.2951535 | F21: ='Income Statement'!E8/'Balance Sheet'!E6 -> 0.29053893 | G21: ='Income Statement'!F8/'Balance Sheet'!F6 -> 0.34956663 | H21: ='Income Statement'!G8/'Balance Sheet'!G6 -> 0.35566811 | I21: ='Income Statement'!H8/'Balance Sheet'!H6 -> 0.31116512 | J21: ='Income Statement'!I8/'Balance Sheet'!I6 -> 0.32198787 | K21: ='Income Statement'!J8/'Balance Sheet'!J6 -> 0.39158625 | ... M21: ='Income Statement'!L8/'Balance Sheet'!L6 -> 0.43773384 | N21: 0.4
B22: Receivables Collection Period (Days) | C22: Efficiency | D22: ='Balance Sheet'!C10/'Income Statement'!C8*365 -> 114.19785 | E22: ='Balance Sheet'!D10/'Income Statement'!D8*365 -> 154.2849 | F22: ='Balance Sheet'!E10/'Income Statement'!E8*365 -> 156.63206 | G22: ='Balance Sheet'!F10/'Income Statement'!F8*365 -> 130.7138 | H22: ='Balance Sheet'!G10/'Income Statement'!G8*365 -> 125.87105 | I22: ='Balance Sheet'!H10/'Income Statement'!H8*365 -> 156.72084 | J22: ='Balance Sheet'!I10/'Income Statement'!I8*365 -> 157.46251 | K22: ='Balance Sheet'!J10/'Income Statement'!J8*365 -> 131.52522 | ... M22: ='Balance Sheet'!L10/'Income Statement'!L8*365 -> 119.83987 | N22: 90
B23: VALUATION RATIOS
B24: Price to Earnings Ratio | C24: Valuation | D24: =D29/'Income Statement'!C23 -> 8.1009245 | E24: =E29/'Income Statement'!D23 -> 10.202761 | F24: =F29/'Income Statement'!E23 -> 9.797619 | G24: =G29/'Income Statement'!F23 -> 8.4025355 | H24: =H29/'Income Statement'!G23 -> 7.8025327 | I24: =I29/'Income Statement'!H23 -> 11.206102 | J24: =J29/'Income Statement'!I23 -> 10.026857 | K24: =K29/'Income Statement'!J23 -> 7.2022528 | ... M24: =M29/'Income Statement'!L23 -> 7.15527 | N24: N/A
B25: Price to Book Ratio | C25: Valuation | D25: =D29/('Balance Sheet'!C12/'DCF Valuation'!$C$10) -> 1.5533436 | E25: =E29/('Balance Sheet'!D12/'DCF Valuation'!$C$10) -> 1.4054282 | F25: =F29/('Balance Sheet'!E12/'DCF Valuation'!$C$10) -> 1.3411023 | G25: =G29/('Balance Sheet'!F12/'DCF Valuation'!$C$10) -> 1.467418 | H25: =H29/('Balance Sheet'!G12/'DCF Valuation'!$C$10) -> 1.348054 | I25: =I29/('Balance Sheet'!H12/'DCF Valuation'!$C$10) -> 1.2964336 | J25: =J29/('Balance Sheet'!I12/'DCF Valuation'!$C$10) -> 1.2509426 | K25: =K29/('Balance Sheet'!J12/'DCF Valuation'!$C$10) -> 1.3650421 | ... M25: =M29/('Balance Sheet'!L12/'DCF Valuation'!$C$10) -> 1.6433128 | N25: N/A
B26: EV to EBITDA | C26: Valuation | D26: =(('Balance Sheet'!C19-'Balance Sheet'!C9)+D29*'DCF Valuation'!$C$10)/'Income Statement'!C14 -> 4.7054855 | E26: =(('Balance Sheet'!D19-'Balance Sheet'!D9)+E29*'DCF Valuation'!$C$10)/'Income Statement'!D14 -> 6.3057022 | F26: =(('Balance Sheet'!E19-'Balance Sheet'!E9)+F29*'DCF Valuation'!$C$10)/'Income Statement'!E14 -> 6.171087 | G26: =(('Balance Sheet'!F19-'Balance Sheet'!F9)+G29*'DCF Valuation'!$C$10)/'Income Statement'!F14 -> 5.3877178 | H26: =(('Balance Sheet'!G19-'Balance Sheet'!G9)+H29*'DCF Valuation'!$C$10)/'Income Statement'!G14 -> 5.0500381 | I26: =(('Balance Sheet'!H19-'Balance Sheet'!H9)+I29*'DCF Valuation'!$C$10)/'Income Statement'!H14 -> 6.3305334 | J26: =(('Balance Sheet'!I19-'Balance Sheet'!I9)+J29*'DCF Valuation'!$C$10)/'Income Statement'!I14 -> 5.8325372 | K26: =(('Balance Sheet'!J19-'Balance Sheet'!J9)+K29*'DCF Valuation'!$C$10)/'Income Statement'!J14 -> 4.6568562 | ... M26: =(('Balance Sheet'!L19-'Balance Sheet'!L9)+M29*'DCF Valuation'!$C$10)/'Income Statement'!L14 -> 4.7800232 | N26: N/A
B27: Dividend Yield | C27: Valuation | D27: ='Income Statement'!C24/D29 -> 0.051569252 | E27: ='Income Statement'!D24/E29 -> 0.041542041 | F27: ='Income Statement'!E24/F29 -> 0.044902449 | G27: ='Income Statement'!F24/G29 -> 0.049251379 | H27: ='Income Statement'!G24/H29 -> 0.05033035 | I27: ='Income Statement'!H24/I29 -> 0.031255209 | J27: ='Income Statement'!I24/J29 -> 0.039898657 | K27: ='Income Statement'!J24/K29 -> 0.056197816 | ... M27: ='Income Statement'!L24/M29 -> 0.055251417 | N27: N/A
B28: Dividend Payout Ratio | C28: Valuation | D28: ='Income Statement'!C24/'Income Statement'!C23 -> 0.41775862 | E28: ='Income Statement'!D24/'Income Statement'!D23 -> 0.42384352 | F28: ='Income Statement'!E24/'Income Statement'!E23 -> 0.43993709 | G28: ='Income Statement'!F24/'Income Statement'!F23 -> 0.41383646 | H28: ='Income Statement'!G24/'Income Statement'!G23 -> 0.3927042 | I28: ='Income Statement'!H24/'Income Statement'!H23 -> 0.35024906 | J28: ='Income Statement'!I24/'Income Statement'!I23 -> 0.40005814 | K28: ='Income Statement'!J24/'Income Statement'!J23 -> 0.40475088 | ... M28: ='Income Statement'!L24/'Income Statement'!L23 -> 0.39533881 | N28: N/A
B29: Historical Market Price (PKR) — Input | D29: 96.957 | E29: 90.27 | F29: 89.082 | G29: 106.596 | H29: 109.278 | I29: 95.984 | J29: 100.254 | K29: 124.56 | L29: 168.064 | M29: 217.189
B30: Note: Historical market price inputs are editable; valuation ratios recalculate automatically.

Sheet DCF Valuation
B1: OGDCL — DCF VALUATION MODEL | Base Year: FY2024 Actuals | PKR Millions unless stated
B2: Blue cells are assumptions you can change | Model projects 5 years of Free Cash Flow and adds a Terminal Value | For academic use only
B3: MODEL ASSUMPTIONS (Change blue cells to run your own scenarios)
B4: Base Year Revenue (PKR Millions) | C4: ='Income Statement'!L6 -> 445680 | D4: FY2024 from OGDCL Annual Report
B5: Base Year Free Cash Flow (PKR M) | C5: ='Cash Flow'!L14 -> 65920 | D5: FY2024 FCF from Cash Flow Statement
B6: Revenue Growth Rate (Annual) | C6: 0.08 | D6: Base case assumes 8% CAGR
B7: FCF to Revenue Margin | C7: =C5/C4 -> 0.14790881 | D7: 10-year historical average FCF margin
B8: WACC | C8: 0.145 | D8: Ke=16% CAPM, Kd=12%, D/V=20%
B9: Terminal Growth Rate | C9: 0.03 | D9: Equal to long-run Pakistan nominal GDP growth
B10: Shares Outstanding (Millions) | C10: 4300.825 | D10: As per PSX — 4,300,825,000 shares
B12: 5-YEAR FREE CASH FLOW PROJECTION — BASE CASE
C13: FY2025E | D13: FY2026E | E13: FY2027E | F13: FY2028E | G13: FY2029E
B14: Projected Revenue (PKR M) | C14: =$C$4*(1+$C$6) -> 481334.4 | D14: =C14*(1+$C$6) -> 519841.15 | E14: =D14*(1+$C$6) -> 561428.44 | F14: =E14*(1+$C$6) -> 606342.72 | G14: =F14*(1+$C$6) -> 654850.14
B15: Projected FCF (PKR M) | C15: =C14*$C$7 -> 71193.6 | D15: =D14*$C$7 -> 76889.088 | E15: =E14*$C$7 -> 83040.215 | F15: =F14*$C$7 -> 89683.432 | G15: =G14*$C$7 -> 96858.107
B16: Present Value of FCF (PKR M) | C16: =C15/(1+$C$8)^1 -> 62177.817 | D16: =D15/(1+$C$8)^2 -> 58648.072 | E16: =E15/(1+$C$8)^3 -> 55318.705 | F16: =F15/(1+$C$8)^4 -> 52178.342 | G16: =G15/(1+$C$8)^5 -> 49216.253
B18: VALUATION SUMMARY
B19: Sum of Present Value of FCFs (PKR M) | C19: =SUM(C16:G16) -> 277539.19
B20: Terminal Value (PKR M) | C20: =G15*(1+$C$9)/($C$8-$C$9) -> 867511.74
B21: Present Value of Terminal Value (PKR M) | C21: =C20/(1+$C$8)^5 -> 440806.44
B22: Total Enterprise Value (PKR M) | C22: =C19+C21 -> 718345.62
B23: Intrinsic Value Per Share (PKR) | C23: =(C22-'Balance Sheet'!L19+'Balance Sheet'!L9)/C10 -> 171.76835
B24: Current Market Price (PKR) | C24: 274.13
B25: Implied Upside or Downside | C25: =C23/C24-1 -> -0.37340549
B28: SENSITIVITY ANALYSIS — INTRINSIC VALUE PER SHARE (PKR)
B29: WACC vs Growth Rate | C29: 0.05 | D29: 0.07 | E29: 0.08 | F29: 0.1 | G29: 0.12
B30: 0.12 | C30: =(($C$4*(1+C$29)^1*$C$7)/(1+$B30)^1+($C$4*(1+C$29)^2*$C$7)/(1+$B30)^2+($C$4*(1+C$29)^3*$C$7)/(1+$B30)^3+($C$4*(1+C$29)^4*$C$7)/(1+$B30)^4+($C$4*(1+C$29)^5*$C$7)/(1+$B30)^5+($C$4*(1+C$29)^5*$C$7*(1+$C$9)/($B30-$C$9))/(1+$B30)^5-'Balance Sheet'!L19+'Balance Sheet'!L9)/$C$10 -> 195.18609 | D30: =(($C$4*(1+D$29)^1*$C$7)/(1+$B30)^1+($C$4*(1+D$29)^2*$C$7)/(1+$B30)^2+($C$4*(1+D$29)^3*$C$7)/(1+$B30)^3+($C$4*(1+D$29)^4*$C$7)/(1+$B30)^4+($C$4*(1+D$29)^5*$C$7)/(1+$B30)^5+($C$4*(1+D$29)^5*$C$7*(1+$C$9)/($B30-$C$9))/(1+$B30)^5-'Balance Sheet'!L19+'Balance Sheet'!L9)/$C$10 -> 211.3079 | E30: =(($C$4*(1+E$29)^1*$C$7)/(1+$B30)^1+($C$4*(1+E$29)^2*$C$7)/(1+$B30)^2+($C$4*(1+E$29)^3*$C$7)/(1+$B30)^3+($C$4*(1+E$29)^4*$C$7)/(1+$B30)^4+($C$4*(1+E$29)^5*$C$7)/(1+$B30)^5+($C$4*(1+E$29)^5*$C$7*(1+$C$9)/($B30-$C$9))/(1+$B30)^5-'Balance Sheet'!L19+'Balance Sheet'!L9)/$C$10 -> 219.79698 | F30: =(($C$4*(1+F$29)^1*$C$7)/(1+$B30)^1+($C$4*(1+F$29)^2*$C$7)/(1+$B30)^2+($C$4*(1+F$29)^3*$C$7)/(1+$B30)^3+($C$4*(1+F$29)^4*$C$7)/(1+$B30)^4+($C$4*(1+F$29)^5*$C$7)/(1+$B30)^5+($C$4*(1+F$29)^5*$C$7*(1+$C$9)/($B30-$C$9))/(1+$B30)^5-'Balance Sheet'!L19+'Balance Sheet'!L9)/$C$10 -> 237.67064 | G30: =(($C$4*(1+G$29)^1*$C$7)/(1+$B30)^1+($C$4*(1+G$29)^2*$C$7)/(1+$B30)^2+($C$4*(1+G$29)^3*$C$7)/(1+$B30)^3+($C$4*(1+G$29)^4*$C$7)/(1+$B30)^4+($C$4*(1+G$29)^5*$C$7)/(1+$B30)^5+($C$4*(1+G$29)^5*$C$7*(1+$C$9)/($B30-$C$9))/(1+$B30)^5-'Balance Sheet'!L19+'Balance Sheet'!L9)/$C$10 -> 256.79208
B31: 0.13 | C31: =(($C$4*(1+C$29)^1*$C$7)/(1+$B31)^1+($C$4*(1+C$29)^2*$C$7)/(1+$B31)^2+($C$4*(1+C$29)^3*$C$7)/(1+$B31)^3+($C$4*(1+C$29)^4*$C$7)/(1+$B31)^4+($C$4*(1+C$29)^5*$C$7)/(1+$B31)^5+($C$4*(1+C$29)^5*$C$7*(1+$C$9)/($B31-$C$9))/(1+$B31)^5-'Balance Sheet'!L19+'Balance Sheet'!L9)/$C$10 -> 175.91972 | D31: =(($C$4*(1+D$29)^1*$C$7)/(1+$B31)^1+($C$4*(1+D$29)^2*$C$7)/(1+$B31)^2+($C$4*(1+D$29)^3*$C$7)/(1+$B31)^3+($C$4*(1+D$29)^4*$C$7)/(1+$B31)^4+($C$4*(1+D$29)^5*$C$7)/(1+$B31)^5+($C$4*(1+D$29)^5*$C$7*(1+$C$9)/($B31-$C$9))/(1+$B31)^5-'Balance Sheet'!L19+'Balance Sheet'!L9)/$C$10 -> 190.18192 | E31: =(($C$4*(1+E$29)^1*$C$7)/(1+$B31)^1+($C$4*(1+E$29)^2*$C$7)/(1+$B31)^2+($C$4*(1+E$29)^3*$C$7)/(1+$B31)^3+($C$4*(1+E$29)^4*$C$7)/(1+$B31)^4+($C$4*(1+E$29)^5*$C$7)/(1+$B31)^5+($C$4*(1+E$29)^5*$C$7*(1+$C$9)/($B31-$C$9))/(1+$B31)^5-'Balance Sheet'!L19+'Balance Sheet'!L9)/$C$10 -> 197.68837 | F31: =(($C$4*(1+F$29)^1*$C$7)/(1+$B31)^1+($C$4*(1+F$29)^2*$C$7)/(1+$B31)^2+($C$4*(1+F$29)^3*$C$7)/(1+$B31)^3+($C$4*(1+F$29)^4*$C$7)/(1+$B31)^4+($C$4*(1+F$29)^5*$C$7)/(1+$B31)^5+($C$4*(1+F$29)^5*$C$7*(1+$C$9)/($B31-$C$9))/(1+$B31)^5-'Balance Sheet'!L19+'Balance Sheet'!L9)/$C$10 -> 213.48609 | G31: =(($C$4*(1+G$29)^1*$C$7)/(1+$B31)^1+($C$4*(1+G$29)^2*$C$7)/(1+$B31)^2+($C$4*(1+G$29)^3*$C$7)/(1+$B31)^3+($C$4*(1+G$29)^4*$C$7)/(1+$B31)^4+($C$4*(1+G$29)^5*$C$7)/(1+$B31)^5+($C$4*(1+G$29)^5*$C$7*(1+$C$9)/($B31-$C$9))/(1+$B31)^5-'Balance Sheet'!L19+'Balance Sheet'!L9)/$C$10 -> 230.37719
B32: 0.145 | C32: =(($C$4*(1+C$29)^1*$C$7)/(1+$B32)^1+($C$4*(1+C$29)^2*$C$7)/(1+$B32)^2+($C$4*(1+C$29)^3*$C$7)/(1+$B32)^3+($C$4*(1+C$29)^4*$C$7)/(1+$B32)^4+($C$4*(1+C$29)^5*$C$7)/(1+$B32)^5+($C$4*(1+C$29)^5*$C$7*(1+$C$9)/($B32-$C$9))/(1+$B32)^5-'Balance Sheet'!L19+'Balance Sheet'!L9)/$C$10 -> 153.31495 | D32: =(($C$4*(1+D$29)^1*$C$7)/(1+$B32)^1+($C$4*(1+D$29)^2*$C$7)/(1+$B32)^2+($C$4*(1+D$29)^3*$C$7)/(1+$B32)^3+($C$4*(1+D$29)^4*$C$7)/(1+$B32)^4+($C$4*(1+D$29)^5*$C$7)/(1+$B32)^5+($C$4*(1+D$29)^5*$C$7*(1+$C$9)/($B32-$C$9))/(1+$B32)^5-'Balance Sheet'!L19+'Balance Sheet'!L9)/$C$10 -> 165.40793 | E32: =(($C$4*(1+E$29)^1*$C$7)/(1+$B32)^1+($C$4*(1+E$29)^2*$C$7)/(1+$B32)^2+($C$4*(1+E$29)^3*$C$7)/(1+$B32)^3+($C$4*(1+E$29)^4*$C$7)/(1+$B32)^4+($C$4*(1+E$29)^5*$C$7)/(1+$B32)^5+($C$4*(1+E$29)^5*$C$7*(1+$C$9)/($B32-$C$9))/(1+$B32)^5-'Balance Sheet'!L19+'Balance Sheet'!L9)/$C$10 -> 171.76835 | F32: =(($C$4*(1+F$29)^1*$C$7)/(1+$B32)^1+($C$4*(1+F$29)^2*$C$7)/(1+$B32)^2+($C$4*(1+F$29)^3*$C$7)/(1+$B32)^3+($C$4*(1+F$29)^4*$C$7)/(1+$B32)^4+($C$4*(1+F$29)^5*$C$7)/(1+$B32)^5+($C$4*(1+F$29)^5*$C$7*(1+$C$9)/($B32-$C$9))/(1+$B32)^5-'Balance Sheet'!L19+'Balance Sheet'!L9)/$C$10 -> 185.1454 | G32: =(($C$4*(1+G$29)^1*$C$7)/(1+$B32)^1+($C$4*(1+G$29)^2*$C$7)/(1+$B32)^2+($C$4*(1+G$29)^3*$C$7)/(1+$B32)^3+($C$4*(1+G$29)^4*$C$7)/(1+$B32)^4+($C$4*(1+G$29)^5*$C$7)/(1+$B32)^5+($C$4*(1+G$29)^5*$C$7*(1+$C$9)/($B32-$C$9))/(1+$B32)^5-'Balance Sheet'!L19+'Balance Sheet'!L9)/$C$10 -> 199.43637
B33: 0.16 | C33: =(($C$4*(1+C$29)^1*$C$7)/(1+$B33)^1+($C$4*(1+C$29)^2*$C$7)/(1+$B33)^2+($C$4*(1+C$29)^3*$C$7)/(1+$B33)^3+($C$4*(1+C$29)^4*$C$7)/(1+$B33)^4+($C$4*(1+C$29)^5*$C$7)/(1+$B33)^5+($C$4*(1+C$29)^5*$C$7*(1+$C$9)/($B33-$C$9))/(1+$B33)^5-'Balance Sheet'!L19+'Balance Sheet'!L9)/$C$10 -> 135.93891 | D33: =(($C$4*(1+D$29)^1*$C$7)/(1+$B33)^1+($C$4*(1+D$29)^2*$C$7)/(1+$B33)^2+($C$4*(1+D$29)^3*$C$7)/(1+$B33)^3+($C$4*(1+D$29)^4*$C$7)/(1+$B33)^4+($C$4*(1+D$29)^5*$C$7)/(1+$B33)^5+($C$4*(1+D$29)^5*$C$7*(1+$C$9)/($B33-$C$9))/(1+$B33)^5-'Balance Sheet'!L19+'Balance Sheet'!L9)/$C$10 -> 146.37705 | E33: =(($C$4*(1+E$29)^1*$C$7)/(1+$B33)^1+($C$4*(1+E$29)^2*$C$7)/(1+$B33)^2+($C$4*(1+E$29)^3*$C$7)/(1+$B33)^3+($C$4*(1+E$29)^4*$C$7)/(1+$B33)^4+($C$4*(1+E$29)^5*$C$7)/(1+$B33)^5+($C$4*(1+E$29)^5*$C$7*(1+$C$9)/($B33-$C$9))/(1+$B33)^5-'Balance Sheet'!L19+'Balance Sheet'!L9)/$C$10 -> 151.86341 | F33: =(($C$4*(1+F$29)^1*$C$7)/(1+$B33)^1+($C$4*(1+F$29)^2*$C$7)/(1+$B33)^2+($C$4*(1+F$29)^3*$C$7)/(1+$B33)^3+($C$4*(1+F$29)^4*$C$7)/(1+$B33)^4+($C$4*(1+F$29)^5*$C$7)/(1+$B33)^5+($C$4*(1+F$29)^5*$C$7*(1+$C$9)/($B33-$C$9))/(1+$B33)^5-'Balance Sheet'!L19+'Balance Sheet'!L9)/$C$10 -> 163.39465 | G33: =(($C$4*(1+G$29)^1*$C$7)/(1+$B33)^1+($C$4*(1+G$29)^2*$C$7)/(1+$B33)^2+($C$4*(1+G$29)^3*$C$7)/(1+$B33)^3+($C$4*(1+G$29)^4*$C$7)/(1+$B33)^4+($C$4*(1+G$29)^5*$C$7)/(1+$B33)^5+($C$4*(1+G$29)^5*$C$7*(1+$C$9)/($B33-$C$9))/(1+$B33)^5-'Balance Sheet'!L19+'Balance Sheet'!L9)/$C$10 -> 175.70358
B34: 0.17 | C34: =(($C$4*(1+C$29)^1*$C$7)/(1+$B34)^1+($C$4*(1+C$29)^2*$C$7)/(1+$B34)^2+($C$4*(1+C$29)^3*$C$7)/(1+$B34)^3+($C$4*(1+C$29)^4*$C$7)/(1+$B34)^4+($C$4*(1+C$29)^5*$C$7)/(1+$B34)^5+($C$4*(1+C$29)^5*$C$7*(1+$C$9)/($B34-$C$9))/(1+$B34)^5-'Balance Sheet'!L19+'Balance Sheet'!L9)/$C$10 -> 126.42942 | D34: =(($C$4*(1+D$29)^1*$C$7)/(1+$B34)^1+($C$4*(1+D$29)^2*$C$7)/(1+$B34)^2+($C$4*(1+D$29)^3*$C$7)/(1+$B34)^3+($C$4*(1+D$29)^4*$C$7)/(1+$B34)^4+($C$4*(1+D$29)^5*$C$7)/(1+$B34)^5+($C$4*(1+D$29)^5*$C$7*(1+$C$9)/($B34-$C$9))/(1+$B34)^5-'Balance Sheet'!L19+'Balance Sheet'!L9)/$C$10 -> 135.96803 | E34: =(($C$4*(1+E$29)^1*$C$7)/(1+$B34)^1+($C$4*(1+E$29)^2*$C$7)/(1+$B34)^2+($C$4*(1+E$29)^3*$C$7)/(1+$B34)^3+($C$4*(1+E$29)^4*$C$7)/(1+$B34)^4+($C$4*(1+E$29)^5*$C$7)/(1+$B34)^5+($C$4*(1+E$29)^5*$C$7*(1+$C$9)/($B34-$C$9))/(1+$B34)^5-'Balance Sheet'!L19+'Balance Sheet'!L9)/$C$10 -> 140.97936 | F34: =(($C$4*(1+F$29)^1*$C$7)/(1+$B34)^1+($C$4*(1+F$29)^2*$C$7)/(1+$B34)^2+($C$4*(1+F$29)^3*$C$7)/(1+$B34)^3+($C$4*(1+F$29)^4*$C$7)/(1+$B34)^4+($C$4*(1+F$29)^5*$C$7)/(1+$B34)^5+($C$4*(1+F$29)^5*$C$7*(1+$C$9)/($B34-$C$9))/(1+$B34)^5-'Balance Sheet'!L19+'Balance Sheet'!L9)/$C$10 -> 151.50771 | G34: =(($C$4*(1+G$29)^1*$C$7)/(1+$B34)^1+($C$4*(1+G$29)^2*$C$7)/(1+$B34)^2+($C$4*(1+G$29)^3*$C$7)/(1+$B34)^3+($C$4*(1+G$29)^4*$C$7)/(1+$B34)^4+($C$4*(1+G$29)^5*$C$7)/(1+$B34)^5+($C$4*(1+G$29)^5*$C$7*(1+$C$9)/($B34-$C$9))/(1+$B34)^5-'Balance Sheet'!L19+'Balance Sheet'!L9)/$C$10 -> 162.73999

Sheet Data Sources
B1: DATA SOURCES, METHODOLOGY AND DISCLAIMER
B3: Source | C3: Detail and URL
B4: OGDCL Annual Reports FY2015 to FY2024 | C4: Full audited accounts — Income Statement, Balance Sheet, Cash Flow. Available at ogdcl.com/all-financial-reports
B5: Pakistan Stock Exchange Data Portal | C5: Live price, P/E, market cap, company profile and announcements. Available at dps.psx.com.pk/company/OGDC
B6: PSX Financial Statements Database | C6: Structured financial data for all PSX-listed companies. Available at financials.psx.com.pk
B7: OGDCL Quarterly Result Announcements | C7: Quarterly press releases and result announcements uploaded to PSX announcements portal
B8: KPMG Taseer Hadi and Co. | C8: Official auditor of OGDCL. All financial statements are independently audited and certified annually
B10: DISCLAIMER
B11: All financial data in this workbook is sourced exclusively from OGDCL official annual reports and the Pakistan Stock Exchange official portal. All figures are in PKR Millions unless stated. The fiscal year runs from July to June. The DCF valuation model is for educational and academic purposes only and does not constitute investment advice or a recommendation to buy or sell securities. Past financial performance is not indicative of future results. CAGR figures are calculated over a 9-year period from FY2015 to FY2024. This workbook was prepared as an academic portfolio project to demonstrate financial analysis skills.
